{"time": "2025-12-15 13:47:16", "action": "open"}
{"time": "2025-12-15 13:47:16", "action": "open"}
{"time": "2025-12-15 13:47:16", "action": "login"}
{"time": "2025-12-15 13:47:16", "action": "open"}
{"time": "2025-12-15 13:47:16", "action": "purchase"}
{"time": "2025-12-15 13:47:16", "action": "purchase"}
{"time": "2025-12-15 13:47:16", "action": "click"}
{"time": "2025-12-15 13:47:16", "action": "click"}
{"time": "2025-12-15 13:47:16", "action": "close"}
{"time": "2025-12-15 13:47:16", "action": "logout"}
{"time": "2025-12-15 13:47:16", "action": "open"}
{"time": "2025-12-15 13:47:16", "action": "view"}
{"time": "2025-12-15 13:47:16", "action": "click"}
{"time": "2025-12-15 13:47:16", "action": "open"}
{"time": "2025-12-15 13:47:16", "action": "purchase"}
{"time": "2025-12-15 13:47:16", "action": "click"}
{"time": "2025-12-15 13:47:16", "action": "login"}
{"time": "2025-12-15 13:47:16", "action": "purchase"}
{"time": "2025-12-15 13:47:16", "action": "logout"}
{"time": "2025-12-15 13:47:16", "action": "logout"}
